birman/__init__.py
birman/decoder.py
birman/encoder.py
birman-0.0.2.dist-info/LICENSE
birman-0.0.2.dist-info/METADATA
birman-0.0.2.dist-info/WHEEL
birman-0.0.2.dist-info/top_level.txt
birman-0.0.2.dist-info/RECORD
