Metadata-Version: 2.1
Name: birman
Version: 0.0.2
Summary: Multipart formdata decoder
Home-page: https://github.com/joegasewicz/birman
Author: Joe Gasewicz
Author-email: joegasewicz@gmail.com
Classifier: Programming Language :: Python :: 3.10
Classifier: Programming Language :: Python :: 3.11
Classifier: License :: OSI Approved :: MIT License
Classifier: Operating System :: OS Independent
License-File: LICENSE
